kuwa/executor/__init__.py
kuwa/executor/cli.py
kuwa/executor/llm_executor.py
kuwa/executor/logger.py
kuwa/executor/metrics.py
kuwa/executor/util.py
kuwa/executor/example/.gitkeep
kuwa/executor/example/chatgpt.py
kuwa/executor/example/debug.py
kuwa/executor/example/dummy.py
kuwa/executor/example/geminipro.py
kuwa/executor/example/huggingface.py
kuwa/executor/example/llamacpp.py
kuwa_executor-0.1.0.dist-info/METADATA
kuwa_executor-0.1.0.dist-info/WHEEL
kuwa_executor-0.1.0.dist-info/entry_points.txt
kuwa_executor-0.1.0.dist-info/RECORD
