Metadata-Version: 2.3
Name: kuwa-executor
Version: 0.1.0
Summary: A framework to serve the Kuwa Executors, including LLM model executor.
Project-URL: Homepage, https://kuwaai.org/os/Intro
Project-URL: Bug Tracker, https://github.com/kuwaai/genai-os/issues
Author-email: Drift <taifu9920923@gmail.com>, Yung-Hsiang Hu <iftnt1999@gmail.com>
Classifier: Operating System :: OS Independent
Classifier: Programming Language :: Python :: 3
Requires-Python: >=3.7
Requires-Dist: fastapi~=0.110.0
Requires-Dist: prometheus-client~=0.20.0
Requires-Dist: python-multipart~=0.0.9
Requires-Dist: pyyaml~=6.0.1
Requires-Dist: requests~=2.31.0
Requires-Dist: retry~=0.9.2
Requires-Dist: uvicorn[standard]~=0.29.0
